not_particularly/__init__.py
not_particularly-2.5.0.dist-info/METADATA
not_particularly-2.5.0.dist-info/WHEEL
not_particularly-2.5.0.dist-info/top_level.txt
not_particularly-2.5.0.dist-info/RECORD
